odoo/addons/mail_activity_creator/README.rst
odoo/addons/mail_activity_creator/__init__.py
odoo/addons/mail_activity_creator/__manifest__.py
odoo/addons/mail_activity_creator/i18n/mail_activity_creator.pot
odoo/addons/mail_activity_creator/models/__init__.py
odoo/addons/mail_activity_creator/models/mail_activity.py
odoo/addons/mail_activity_creator/readme/CONTRIBUTORS.rst
odoo/addons/mail_activity_creator/readme/DESCRIPTION.rst
odoo/addons/mail_activity_creator/static/description/icon.png
odoo/addons/mail_activity_creator/static/description/index.html
odoo/addons/mail_activity_creator/static/src/xml/activity.xml
odoo/addons/mail_activity_creator/tests/__init__.py
odoo/addons/mail_activity_creator/tests/test_creator.py
odoo/addons/mail_activity_creator/views/mail_activity_views.xml
odoo11_addon_mail_activity_creator-11.0.1.0.0.99.dev3.dist-info/METADATA
odoo11_addon_mail_activity_creator-11.0.1.0.0.99.dev3.dist-info/WHEEL
odoo11_addon_mail_activity_creator-11.0.1.0.0.99.dev3.dist-info/top_level.txt
odoo11_addon_mail_activity_creator-11.0.1.0.0.99.dev3.dist-info/RECORD
